{
"type": "FeatureCollection",
"crs": { "type": "name", "properties": { "name": "urn:ogc:def:crs:EPSG::2062" } },
"features": [
{ "type": "Feature", "properties": { "farm ID": 100, "cage count": 5 }, "geometry": { "type": "Point", "coordinates": [ 0.035492848791735, 38.616120444320991 ] } },
{ "type": "Feature", "properties": { "farm ID": 119, "cage count": 18 }, "geometry": { "type": "Point", "coordinates": [ -0.033773684590718, 38.5714297061322 ] } },
{ "type": "Feature", "properties": { "farm ID": 506, "cage count": 4 }, "geometry": { "type": "Point", "coordinates": [ 3.1058726573595, 42.208334650786973 ] } },
{ "type": "Feature", "properties": { "farm ID": 513, "cage count": 6 }, "geometry": { "type": "Point", "coordinates": [ 3.169832011432075, 42.255952275368934 ] } },
{ "type": "Feature", "properties": { "farm ID": 525, "cage count": 5 }, "geometry": { "type": "Point", "coordinates": [ 3.116279793294986, 42.232724560999948 ] } }
]
}
