{
"type": "FeatureCollection",
"crs": { "type": "name", "properties": { "name": "urn:ogc:def:crs:EPSG::3034" } },
"features": [
{ "type": "Feature", "properties": { "farm ID": 46, "cage ID": 24, "radius": 9.08, "diameter": 9.08 }, "geometry": { "type": "Point", "coordinates": [ 14.403915241532049, 35.963791963341457 ] } },
{ "type": "Feature", "properties": { "farm ID": 46, "cage ID": 25, "radius": 10.12, "diameter": 10.12 }, "geometry": { "type": "Point", "coordinates": [ 14.404333013337736, 35.963862823850249 ] } },
{ "type": "Feature", "properties": { "farm ID": 46, "cage ID": 26, "radius": 9.84, "diameter": 9.84 }, "geometry": { "type": "Point", "coordinates": [ 14.404341272561561, 35.96198801546484 ] } },
{ "type": "Feature", "properties": { "farm ID": 46, "cage ID": 27, "radius": 8.52, "diameter": 8.52 }, "geometry": { "type": "Point", "coordinates": [ 14.404747516872135, 35.963983892800478 ] } },
{ "type": "Feature", "properties": { "farm ID": 46, "cage ID": 28, "radius": 9.35, "diameter": 9.35 }, "geometry": { "type": "Point", "coordinates": [ 14.404739786494677, 35.962151992534871 ] } },
{ "type": "Feature", "properties": { "farm ID": 46, "cage ID": 29, "radius": 10.22, "diameter": 10.22 }, "geometry": { "type": "Point", "coordinates": [ 14.40511454093089, 35.965200568383764 ] } },
{ "type": "Feature", "properties": { "farm ID": 46, "cage ID": 30, "radius": 8.66, "diameter": 8.66 }, "geometry": { "type": "Point", "coordinates": [ 14.405115220793261, 35.964060829312444 ] } },
{ "type": "Feature", "properties": { "farm ID": 46, "cage ID": 31, "radius": 10.04, "diameter": 10.04 }, "geometry": { "type": "Point", "coordinates": [ 14.405167301279063, 35.962318762380463 ] } },
{ "type": "Feature", "properties": { "farm ID": 46, "cage ID": 32, "radius": 9.76, "diameter": 9.76 }, "geometry": { "type": "Point", "coordinates": [ 14.405532708685932, 35.965271191302207 ] } },
{ "type": "Feature", "properties": { "farm ID": 46, "cage ID": 33, "radius": 8.8, "diameter": 8.8 }, "geometry": { "type": "Point", "coordinates": [ 14.405516000064978, 35.964168614924809 ] } },
{ "type": "Feature", "properties": { "farm ID": 46, "cage ID": 34, "radius": 8.57, "diameter": 8.57 }, "geometry": { "type": "Point", "coordinates": [ 14.405563082318382, 35.962459282556402 ] } },
{ "type": "Feature", "properties": { "farm ID": 46, "cage ID": 35, "radius": 8.48, "diameter": 8.48 }, "geometry": { "type": "Point", "coordinates": [ 14.405902235256287, 35.964287581347243 ] } },
{ "type": "Feature", "properties": { "farm ID": 46, "cage ID": 36, "radius": 10.13, "diameter": 10.13 }, "geometry": { "type": "Point", "coordinates": [ 14.405996242388923, 35.965311054938013 ] } },
{ "type": "Feature", "properties": { "farm ID": 46, "cage ID": 37, "radius": 8.71, "diameter": 8.71 }, "geometry": { "type": "Point", "coordinates": [ 14.405905057350434, 35.962586850703758 ] } },
{ "type": "Feature", "properties": { "farm ID": 46, "cage ID": 38, "radius": 9.03, "diameter": 9.03 }, "geometry": { "type": "Point", "coordinates": [ 14.406253119345079, 35.964400022806146 ] } },
{ "type": "Feature", "properties": { "farm ID": 46, "cage ID": 39, "radius": 8.57, "diameter": 8.57 }, "geometry": { "type": "Point", "coordinates": [ 14.406253154683579, 35.962728225180186 ] } },
{ "type": "Feature", "properties": { "farm ID": 46, "cage ID": 40, "radius": 8.66, "diameter": 8.66 }, "geometry": { "type": "Point", "coordinates": [ 14.406449804088853, 35.965352594780917 ] } },
{ "type": "Feature", "properties": { "farm ID": 46, "cage ID": 41, "radius": 9.26, "diameter": 9.26 }, "geometry": { "type": "Point", "coordinates": [ 14.406638283519303, 35.962866239383239 ] } },
{ "type": "Feature", "properties": { "farm ID": 46, "cage ID": 42, "radius": 9.63, "diameter": 9.63 }, "geometry": { "type": "Point", "coordinates": [ 14.407134489572195, 35.962982545103756 ] } }
]
}
