{
"type": "FeatureCollection",
"crs": { "type": "name", "properties": { "name": "urn:ogc:def:crs:EPSG::3034" } },
"features": [
{ "type": "Feature", "properties": { "id": 1, "farm_id": 8, "radius": 9.0766666666666662, "diameter": 18.153333333333332 }, "geometry": { "type": "Point", "coordinates": [ 14.403915241532049, 35.963791963341457 ] } },
{ "type": "Feature", "properties": { "id": 2, "farm_id": 8, "radius": 10.12, "diameter": 20.24 }, "geometry": { "type": "Point", "coordinates": [ 14.404333013337736, 35.963862823850249 ] } },
{ "type": "Feature", "properties": { "id": 3, "farm_id": 8, "radius": 9.844, "diameter": 19.688 }, "geometry": { "type": "Point", "coordinates": [ 14.404341272561561, 35.96198801546484 ] } },
{ "type": "Feature", "properties": { "id": 4, "farm_id": 8, "radius": 8.524, "diameter": 17.048 }, "geometry": { "type": "Point", "coordinates": [ 14.404747516872135, 35.963983892800478 ] } },
{ "type": "Feature", "properties": { "id": 5, "farm_id": 8, "radius": 9.35, "diameter": 18.7 }, "geometry": { "type": "Point", "coordinates": [ 14.404739786494677, 35.962151992534871 ] } },
{ "type": "Feature", "properties": { "id": 6, "farm_id": 8, "radius": 10.22, "diameter": 20.44 }, "geometry": { "type": "Point", "coordinates": [ 14.40511454093089, 35.965200568383764 ] } },
{ "type": "Feature", "properties": { "id": 7, "farm_id": 8, "radius": 8.6625, "diameter": 17.325 }, "geometry": { "type": "Point", "coordinates": [ 14.405115220793261, 35.964060829312444 ] } },
{ "type": "Feature", "properties": { "id": 8, "farm_id": 8, "radius": 10.036666666666667, "diameter": 20.073333333333334 }, "geometry": { "type": "Point", "coordinates": [ 14.405167301279063, 35.962318762380463 ] } },
{ "type": "Feature", "properties": { "id": 9, "farm_id": 8, "radius": 9.76, "diameter": 19.52 }, "geometry": { "type": "Point", "coordinates": [ 14.405532708685932, 35.965271191302207 ] } },
{ "type": "Feature", "properties": { "id": 10, "farm_id": 8, "radius": 8.8, "diameter": 17.6 }, "geometry": { "type": "Point", "coordinates": [ 14.405516000064978, 35.964168614924809 ] } },
{ "type": "Feature", "properties": { "id": 11, "farm_id": 8, "radius": 8.57, "diameter": 17.14 }, "geometry": { "type": "Point", "coordinates": [ 14.405563082318382, 35.962459282556402 ] } },
{ "type": "Feature", "properties": { "id": 12, "farm_id": 8, "radius": 8.4766666666666666, "diameter": 16.953333333333333 }, "geometry": { "type": "Point", "coordinates": [ 14.405902235256287, 35.964287581347243 ] } },
{ "type": "Feature", "properties": { "id": 13, "farm_id": 8, "radius": 10.13, "diameter": 20.26 }, "geometry": { "type": "Point", "coordinates": [ 14.405996242388923, 35.965311054938013 ] } },
{ "type": "Feature", "properties": { "id": 14, "farm_id": 8, "radius": 8.71, "diameter": 17.42 }, "geometry": { "type": "Point", "coordinates": [ 14.405905057350434, 35.962586850703758 ] } },
{ "type": "Feature", "properties": { "id": 15, "farm_id": 8, "radius": 9.0333333333333332, "diameter": 18.066666666666666 }, "geometry": { "type": "Point", "coordinates": [ 14.406253119345079, 35.964400022806146 ] } },
{ "type": "Feature", "properties": { "id": 16, "farm_id": 8, "radius": 8.5733333333333324, "diameter": 17.146666666666665 }, "geometry": { "type": "Point", "coordinates": [ 14.406253154683579, 35.962728225180186 ] } },
{ "type": "Feature", "properties": { "id": 17, "farm_id": 8, "radius": 8.663333333333334, "diameter": 17.326666666666668 }, "geometry": { "type": "Point", "coordinates": [ 14.406449804088853, 35.965352594780917 ] } },
{ "type": "Feature", "properties": { "id": 18, "farm_id": 8, "radius": 9.26, "diameter": 18.52 }, "geometry": { "type": "Point", "coordinates": [ 14.406638283519303, 35.962866239383239 ] } },
{ "type": "Feature", "properties": { "id": 19, "farm_id": 8, "radius": 9.6275, "diameter": 19.255 }, "geometry": { "type": "Point", "coordinates": [ 14.407134489572195, 35.962982545103756 ] } }
]
}
